mlflow_openshift/__init__.py
mlflow_openshift/defaults.py
mlflow_openshift/deployment_client.py
mlflow_openshift/oc_helper.py
mlflow_openshift/utils.py
mlflow_openshift/templates/deploy_with_auth.yml
tests/__init__.py
tests/create_deployment_test.py
tests/delete_deployment_test.py
tests/get_deployment_test.py
tests/list_deployments_test.py
tests/predict_test.py
tests/update_deployment_test.py
mlflow_openshift-0.2.3.dist-info/LICENSE
mlflow_openshift-0.2.3.dist-info/METADATA
mlflow_openshift-0.2.3.dist-info/WHEEL
mlflow_openshift-0.2.3.dist-info/entry_points.txt
mlflow_openshift-0.2.3.dist-info/top_level.txt
mlflow_openshift-0.2.3.dist-info/RECORD
