Metadata-Version: 2.1
Name: mlflow-openshift
Version: 0.2.3
Summary: MLFlow Openshift Deployment Plugin
Home-page: https://github.com/BIX-Digital/mlflow-openshift
Author: sklingel
Classifier: Programming Language :: Python :: 3
Classifier: License :: OSI Approved :: Apache Software License
Classifier: Operating System :: OS Independent
Requires-Python: >=3.6
License-File: LICENSE
Requires-Dist: mlflow (<2.*,>=1.13.*)
Requires-Dist: numpy (>=1.19.*)
Requires-Dist: openshift-client (>=1.0.*)
